include/_c_gradients.c
include/_c_gradients.h
include/_c_integral_image.c
include/_c_integral_image.h
include/_c_integral_to_distance.c
include/_c_integral_to_distance.h
include/_c_interpolation_bicubic.c
include/_c_interpolation_bicubic.h
include/_c_interpolation_catmull_rom.c
include/_c_interpolation_catmull_rom.h
include/_c_interpolation_lanczos.c
include/_c_interpolation_lanczos.h
include/_c_interpolation_nearest_neighbor.c
include/_c_interpolation_nearest_neighbor.h
include/_c_mandelbrot_benchmark.c
include/_c_mandelbrot_benchmark.h
include/_c_patch_distance.c
include/_c_patch_distance.h
include/_c_sr_radial_gradient_convergence.c
include/_c_sr_radial_gradient_convergence.h
include/_c_sr_radiality.c
include/_c_sr_radiality.h
include/_c_template_advanced.c
include/_c_template_advanced.h
include/others/OpenSimplex2/OpenSimplex2F.c
include/others/OpenSimplex2/OpenSimplex2F.h
liquid_benchmarks/_le_channel_registration/ChannelRegistrationEstimator.yml
liquid_benchmarks/_le_convolution/Convolution.yml
liquid_benchmarks/_le_drift_calculator/DriftEstimator.yml
liquid_benchmarks/_le_esrrf/eSRRF.yml
liquid_benchmarks/_le_esrrf3d/eSRRF3D.yml
liquid_benchmarks/_le_interpolation_bicubic/ShiftAndMagnify.yml
liquid_benchmarks/_le_interpolation_bicubic/ShiftScaleRotate.yml
liquid_benchmarks/_le_interpolation_catmull_rom/ShiftAndMagnify.yml
liquid_benchmarks/_le_interpolation_catmull_rom/ShiftScaleRotate.yml
liquid_benchmarks/_le_interpolation_lanczos/ShiftAndMagnify.yml
liquid_benchmarks/_le_interpolation_lanczos/ShiftScaleRotate.yml
liquid_benchmarks/_le_interpolation_nearest_neighbor/PolarTransform.yml
liquid_benchmarks/_le_interpolation_nearest_neighbor/ShiftAndMagnify.yml
liquid_benchmarks/_le_interpolation_nearest_neighbor/ShiftScaleRotate.yml
liquid_benchmarks/_le_nlm_denoising/NLMDenoising.yml
liquid_benchmarks/_le_patch_nlm_denoising/NLMDenoising.yml
liquid_benchmarks/_le_pixel_nlm_denoising/NLMDenoising.yml
nanopyx-1.3.3.dist-info/LICENSE.txt
nanopyx-1.3.3.dist-info/METADATA
nanopyx-1.3.3.dist-info/WHEEL
nanopyx-1.3.3.dist-info/top_level.txt
nanopyx-1.3.3.dist-info/RECORD
