Metadata-Version: 2.1
Name: nanopyx
Version: 1.3.3
Summary: Nanoscopy Python library (NanoPyx, the successor to NanoJ) - focused on light microscopy and super-resolution imaging
Author-email: Ricardo Henriques <ricardo.jv.henriques@gmail.com>, Bruno Saraiva <bruno.msaraiva2@gmail.com>, Inês Cunha <inescunha200@gmail.com>, António Brito <antmsbrito95@gmail.com>
Maintainer-email: Bruno Saraiva <bruno.msaraiva2@gmail.com>
License: Attribution 4.0 International
Project-URL: homepage, https://github.com/HenriquesLab/NanoPyx
Project-URL: documentation, https://henriqueslab.github.io/nanopyx
Project-URL: repository, https://github.com/HenriquesLab/NanoPyx
Project-URL: bug_tracker, https://github.com/HenriquesLab/NanoPyx/issues
Keywords: NanoJ,Super-Resolution Microscopy,Fluorescence,BioImage Analysis
Classifier: Programming Language :: Python :: 3
Classifier: License :: OSI Approved :: MIT License
Classifier: Operating System :: OS Independent
Requires-Python: >=3.9
License-File: LICENSE.txt
Requires-Dist: liquid_engine
Requires-Dist: mako>=1.3.0
Requires-Dist: cython>=0.29.32
Requires-Dist: numpy<2,>=1.22
Requires-Dist: scipy>=1.8
Requires-Dist: tifffile>=2022.5.4
Requires-Dist: scikit-image>=0.19.2
Requires-Dist: pyyaml>=6.0
Requires-Dist: onedrivedownloader>=1.1.3
Requires-Dist: gdown>=4.7.3
Requires-Dist: tqdm>=4.64.1
Requires-Dist: lmfit>=1.1.0
Requires-Dist: opencv-python>=4.7.0.68
Requires-Dist: pyopencl>=2022.3.1
Requires-Dist: scikit-learn>=1.1.0
Requires-Dist: matplotlib>=3.5
Requires-Dist: importlib-resources
Requires-Dist: ezinput>=0.0.2
Provides-Extra: all
Requires-Dist: nanopyx[developer,doc,jupyter,optional,test]; extra == "all"
Provides-Extra: developer
Requires-Dist: pyx2pxd>=0.1.1; extra == "developer"
Requires-Dist: black>=23.1.0; extra == "developer"
Requires-Dist: flake8>=6.0.0; extra == "developer"
Provides-Extra: test
Requires-Dist: nox>=2022.11.21; extra == "test"
Requires-Dist: pytest==7.2; extra == "test"
Requires-Dist: pytest-cov>=4.0.0; extra == "test"
Requires-Dist: pytest-icdiff>=0.6; extra == "test"
Requires-Dist: pytest-clarity>=1.0.1; extra == "test"
Requires-Dist: pytest-timeout>=2.1.0; extra == "test"
Requires-Dist: pytest-plt>=1.1.0; extra == "test"
Requires-Dist: pytest-xdist>=3.1.0; extra == "test"
Requires-Dist: pytest-sugar>=0.9.6; extra == "test"
Requires-Dist: pytest-cython>=0.2.0; extra == "test"
Requires-Dist: nanopyx[jupyter]; extra == "test"
Requires-Dist: nanopyx[optional]; extra == "test"
Provides-Extra: optional
Requires-Dist: numba; extra == "optional"
Requires-Dist: dask<2024.2.0; extra == "optional"
Requires-Dist: dask_image; extra == "optional"
Requires-Dist: transonic; extra == "optional"
Provides-Extra: cuda
Requires-Dist: cupy; extra == "cuda"
Provides-Extra: jupyter
Requires-Dist: nbformat>=4.2.0; extra == "jupyter"
Requires-Dist: seaborn>=0.12.1; extra == "jupyter"
Requires-Dist: celluloid>=0.2.0; extra == "jupyter"
Requires-Dist: jupyterlab>=3.5.3; extra == "jupyter"
Requires-Dist: ipywidgets>=8.0.0; extra == "jupyter"
Requires-Dist: nbmake>=1.3.5; extra == "jupyter"
Requires-Dist: ipyfilechooser>=0.6.0; extra == "jupyter"
Requires-Dist: ipympl>=0.9.3; extra == "jupyter"
Requires-Dist: stackview>=0.6.1; extra == "jupyter"
Requires-Dist: ipycanvas>=0.13; extra == "jupyter"
Provides-Extra: colab
Requires-Dist: stackview>=0.6.1; extra == "colab"
Requires-Dist: ipycanvas==0.11.0; extra == "colab"
Provides-Extra: doc
Requires-Dist: pdoc>=12.3.1; extra == "doc"
Requires-Dist: nanopyx[developer,jupyter]; extra == "doc"
